odoo/addons/product_barcode_required/README.rst
odoo/addons/product_barcode_required/__init__.py
odoo/addons/product_barcode_required/__manifest__.py
odoo/addons/product_barcode_required/i18n/ca.po
odoo/addons/product_barcode_required/i18n/es.po
odoo/addons/product_barcode_required/i18n/it.po
odoo/addons/product_barcode_required/i18n/product_barcode_required.pot
odoo/addons/product_barcode_required/models/__init__.py
odoo/addons/product_barcode_required/models/product_barcode_mixin.py
odoo/addons/product_barcode_required/models/product_product.py
odoo/addons/product_barcode_required/models/product_template.py
odoo/addons/product_barcode_required/models/res_company.py
odoo/addons/product_barcode_required/models/res_config_settings.py
odoo/addons/product_barcode_required/readme/CONFIGURE.md
odoo/addons/product_barcode_required/readme/CONTRIBUTORS.md
odoo/addons/product_barcode_required/readme/DESCRIPTION.md
odoo/addons/product_barcode_required/static/description/icon.png
odoo/addons/product_barcode_required/static/description/index.html
odoo/addons/product_barcode_required/tests/__init__.py
odoo/addons/product_barcode_required/tests/test_barcode.py
odoo/addons/product_barcode_required/views/product_template_view.xml
odoo/addons/product_barcode_required/views/product_view.xml
odoo/addons/product_barcode_required/views/res_config_settings.xml
odoo_addon_product_barcode_required-18.0.1.0.0.2.dist-info/METADATA
odoo_addon_product_barcode_required-18.0.1.0.0.2.dist-info/WHEEL
odoo_addon_product_barcode_required-18.0.1.0.0.2.dist-info/top_level.txt
odoo_addon_product_barcode_required-18.0.1.0.0.2.dist-info/RECORD
